yws_mcp_demo/__init__.py
yws_mcp_demo-0.1.0.dist-info/METADATA
yws_mcp_demo-0.1.0.dist-info/WHEEL
yws_mcp_demo-0.1.0.dist-info/entry_points.txt
yws_mcp_demo-0.1.0.dist-info/RECORD
