Metadata-Version: 2.4
Name: yws-mcp-demo
Version: 0.1.0
Summary: Add your description here
Author-email: yws020 <yws020@qq.com>
Requires-Python: >=3.13
Requires-Dist: mcp[cli]>=1.11.0
